geowebi/__init__.py
geowebi/common.py
geowebi/geowebi.py
geowebi-0.0.1.dist-info/LICENSE
geowebi-0.0.1.dist-info/METADATA
geowebi-0.0.1.dist-info/WHEEL
geowebi-0.0.1.dist-info/entry_points.txt
geowebi-0.0.1.dist-info/top_level.txt
geowebi-0.0.1.dist-info/RECORD
